<?xml version="1.0" encoding="utf-8"?>
<ArrayOfTutor xmlns:xsi="http://www.w3.org/2001/XMLSchema-instance" xmlns:xsd="http://www.w3.org/2001/XMLSchema">
  <Tutor>
    <Id>289664229</Id>
    <FullName>Ariela Klein</FullName>
    <CellNumber>059-2038373</CellNumber>
    <Email>ariela.klein@example.com</Email>
    <Password>$2a$11$ddmuTQIXyeE1nKMCAqvNWuVpDXd214.OSGO9VKoVKD/vFakQuIefq</Password>
    <CurrentAddress>Street 25, City 14</CurrentAddress>
    <Latitude>13.088606175486873</Latitude>
    <Longitude>147.27228080962624</Longitude>
    <Role>Manager</Role>
    <Active>true</Active>
    <Distance>7.478001255845341</Distance>
    <DistanceType>Air</DistanceType>
  </Tutor>
  <Tutor>
    <Id>346081458</Id>
    <FullName>Shira Peretz</FullName>
    <CellNumber>058-9415076</CellNumber>
    <Email>shira.peretz@example.com</Email>
    <Password>$2a$11$Fm57Ur9qdpRc.Uk9q9a7ReoJLLZWwaSl3I066zKNFCrslcZLg0H92</Password>
    <CurrentAddress>Street 8, City 15</CurrentAddress>
    <Latitude>40.93777634522249</Latitude>
    <Longitude>-18.007132779986534</Longitude>
    <Role>MasterTutor</Role>
    <Active>true</Active>
    <Distance>14.487339629312643</Distance>
    <DistanceType>Air</DistanceType>
  </Tutor>
  <Tutor>
    <Id>296186950</Id>
    <FullName>Shira Levin</FullName>
    <CellNumber>050-7310584</CellNumber>
    <Email>shira.levin@example.com</Email>
    <Password>$2a$11$kidQhSbRXDJcqQIh8qqMNOJvd6lpj80oEqha6uuljx2HtU9tX3tby</Password>
    <CurrentAddress>Street 81, City 18</CurrentAddress>
    <Latitude>75.85800389456696</Latitude>
    <Longitude>108.25749903010791</Longitude>
    <Role>MasterTutor</Role>
    <Active>false</Active>
    <Distance>4.1479197670009444</Distance>
    <DistanceType>Air</DistanceType>
  </Tutor>
  <Tutor>
    <Id>263971087</Id>
    <FullName>David Klein</FullName>
    <CellNumber>050-1674147</CellNumber>
    <Email>david.klein@example.com</Email>
    <Password>$2a$11$iy.LGtcdwdtLN6b0xztyfedv0ZdM394rSYsc8i9K92r.juw5c4oyW</Password>
    <CurrentAddress>Street 2, City 9</CurrentAddress>
    <Latitude>-85.36996572367377</Latitude>
    <Longitude>-112.9155114234396</Longitude>
    <Role>MasterTutor</Role>
    <Active>true</Active>
    <Distance>8.987337702137918</Distance>
    <DistanceType>Air</DistanceType>
  </Tutor>
  <Tutor>
    <Id>247392509</Id>
    <FullName>Dani Cohen</FullName>
    <CellNumber>058-7205486</CellNumber>
    <Email>dani.cohen@example.com</Email>
    <Password>$2a$11$BhGoMJcp5mQFMzm/J.U6sekN2urzHFy8vOdEwBxMjZ.Mv1cJptP5O</Password>
    <CurrentAddress>Street 34, City 16</CurrentAddress>
    <Latitude>-68.23478198068086</Latitude>
    <Longitude>-6.580762057590647</Longitude>
    <Role>BeginnerTutor</Role>
    <Active>false</Active>
    <Distance>13.90793217296766</Distance>
    <DistanceType>Air</DistanceType>
  </Tutor>
  <Tutor>
    <Id>331800920</Id>
    <FullName>Shira Klein</FullName>
    <CellNumber>050-3754549</CellNumber>
    <Email>shira.klein@example.com</Email>
    <Password>$2a$11$tIb2x6MtWFli///qLsM/COBwlFIKfBoypAnlF1DtiCjwQOp3n1OL6</Password>
    <CurrentAddress>Street 3, City 5</CurrentAddress>
    <Latitude>-52.69803485923561</Latitude>
    <Longitude>-141.66489050771102</Longitude>
    <Role>BeginnerTutor</Role>
    <Active>false</Active>
    <Distance>4.737010638781209</Distance>
    <DistanceType>Air</DistanceType>
  </Tutor>
  <Tutor>
    <Id>392222261</Id>
    <FullName>David Azoulay</FullName>
    <CellNumber>059-9196866</CellNumber>
    <Email>david.azoulay@example.com</Email>
    <Password>$2a$11$eG1ZFJHJO/bdSqfXLRFKUeQJ823rWbUfVYE8cVTiw25A8WmaHOB7.</Password>
    <CurrentAddress>Street 33, City 16</CurrentAddress>
    <Latitude>16.133212396970563</Latitude>
    <Longitude>12.489178189930385</Longitude>
    <Role>BeginnerTutor</Role>
    <Active>false</Active>
    <Distance>17.005407122921884</Distance>
    <DistanceType>Walking</DistanceType>
  </Tutor>
  <Tutor>
    <Id>274156793</Id>
    <FullName>Rivka Amar</FullName>
    <CellNumber>057-7386263</CellNumber>
    <Email>rivka.amar@example.com</Email>
    <Password>$2a$11$IDT4HB8NQZDMqbxDdqAmDensRWH0Q55QWdT.Xbi/h3ekBOJEeyaka</Password>
    <CurrentAddress>Street 68, City 3</CurrentAddress>
    <Latitude>-80.76160044650118</Latitude>
    <Longitude>-147.76734402399111</Longitude>
    <Role>BeginnerTutor</Role>
    <Active>false</Active>
    <Distance>9.786296128683443</Distance>
    <DistanceType>Air</DistanceType>
  </Tutor>
  <Tutor>
    <Id>264807249</Id>
    <FullName>Dina Israelof</FullName>
    <CellNumber>055-7644778</CellNumber>
    <Email>dina.israelof@example.com</Email>
    <Password>$2a$11$HsvIy9hka.BMGBR.ur2nQu9UqZoCBGZ0AMaNiQ8C38kYPqM5gbBfq</Password>
    <CurrentAddress>Street 69, City 18</CurrentAddress>
    <Latitude>-11.106646776651928</Latitude>
    <Longitude>161.04575096166025</Longitude>
    <Role>MasterTutor</Role>
    <Active>true</Active>
    <Distance>2.8005150267580525</Distance>
    <DistanceType>Driving</DistanceType>
  </Tutor>
  <Tutor>
    <Id>249767708</Id>
    <FullName>Eli Mizrahi</FullName>
    <CellNumber>053-5383196</CellNumber>
    <Email>eli.mizrahi@example.com</Email>
    <Password>$2a$11$MCJ4Q.fXr24kSGxXgKlheu40v7vGRNPi7QHlKLKiiT27vqDrM5niK</Password>
    <CurrentAddress>Street 70, City 19</CurrentAddress>
    <Latitude>-31.947883918301955</Latitude>
    <Longitude>-75.54006186450727</Longitude>
    <Role>BeginnerTutor</Role>
    <Active>true</Active>
    <Distance>12.098515839171391</Distance>
    <DistanceType>Driving</DistanceType>
  </Tutor>
  <Tutor>
    <Id>395198377</Id>
    <FullName>Tamar Peretz</FullName>
    <CellNumber>051-3630157</CellNumber>
    <Email>tamar.peretz@example.com</Email>
    <Password>$2a$11$8yBjdROx0ruggkPxIoOZAeIBSeR3N34dce2HrkCLGVziCeRXF9j5m</Password>
    <CurrentAddress>Street 42, City 16</CurrentAddress>
    <Latitude>-25.656324660296136</Latitude>
    <Longitude>-152.45024907123494</Longitude>
    <Role>MasterTutor</Role>
    <Active>false</Active>
    <Distance>16.09305312631526</Distance>
    <DistanceType>Walking</DistanceType>
  </Tutor>
  <Tutor>
    <Id>279793608</Id>
    <FullName>David Israelof</FullName>
    <CellNumber>054-9130230</CellNumber>
    <Email>david.israelof@example.com</Email>
    <Password>$2a$11$WDZsZ/husKI0er6xhJqAS.cN32SoAGzSAGbSCgpnkOBAV.rnLBApW</Password>
    <CurrentAddress>Street 37, City 15</CurrentAddress>
    <Latitude>86.53016549345975</Latitude>
    <Longitude>-26.646620549727174</Longitude>
    <Role>BeginnerTutor</Role>
    <Active>true</Active>
    <Distance>11.163833025346355</Distance>
    <DistanceType>Air</DistanceType>
  </Tutor>
  <Tutor>
    <Id>276724200</Id>
    <FullName>Eli Cohen</FullName>
    <CellNumber>054-6089127</CellNumber>
    <Email>eli.cohen@example.com</Email>
    <Password>$2a$11$xHrUJxQkQCS3h55KLRalM..ir/TgIUaCEb4a6zSqc4HxlUH3tR/US</Password>
    <CurrentAddress>Street 93, City 13</CurrentAddress>
    <Latitude>85.9953060575825</Latitude>
    <Longitude>36.484291366681106</Longitude>
    <Role>BeginnerTutor</Role>
    <Active>true</Active>
    <Distance>1.1853290771960445</Distance>
    <DistanceType>Walking</DistanceType>
  </Tutor>
  <Tutor>
    <Id>359323896</Id>
    <FullName>Eli Amar</FullName>
    <CellNumber>056-1174170</CellNumber>
    <Email>eli.amar@example.com</Email>
    <Password>$2a$11$uzYVs71ZnM8S0UZKAFYvg.y4N9b8ApBQtbrMBOiiLmXftSmVFc/pS</Password>
    <CurrentAddress>Street 40, City 7</CurrentAddress>
    <Latitude>-32.16164340993321</Latitude>
    <Longitude>165.66456037840408</Longitude>
    <Role>MasterTutor</Role>
    <Active>false</Active>
    <Distance>2.0162154812900557</Distance>
    <DistanceType>Walking</DistanceType>
  </Tutor>
  <Tutor>
    <Id>376893780</Id>
    <FullName>Tamar Sharabi</FullName>
    <CellNumber>054-8393189</CellNumber>
    <Email>tamar.sharabi@example.com</Email>
    <Password>$2a$11$97kD.knGyvb6u7w/pjHcCOVFsHTvdp9DNmO7JeoPTfWpGDq1gDCk2</Password>
    <CurrentAddress>Street 11, City 17</CurrentAddress>
    <Latitude>65.12458829385403</Latitude>
    <Longitude>16.641051819328567</Longitude>
    <Role>MasterTutor</Role>
    <Active>true</Active>
    <Distance>5.406641951119222</Distance>
    <DistanceType>Driving</DistanceType>
  </Tutor>
</ArrayOfTutor>