<?xml version="1.0" encoding="utf-8"?>
<ArrayOfTutor xmlns:xsi="http://www.w3.org/2001/XMLSchema-instance" xmlns:xsd="http://www.w3.org/2001/XMLSchema">
  <Tutor>
    <Id>300851146</Id>
    <FullName>Yair Cohen</FullName>
    <CellNumber>051-5892630</CellNumber>
    <Email>yair.cohen@example.com</Email>
    <Password>$2a$11$qwZB.9LJ0PAwaNj1Pt/pq.IvoEZL1Sa0dUsN.OfljAokrNK.sSrMu</Password>
    <CurrentAddress>Street 63, City 8</CurrentAddress>
    <Latitude>36.47356010675517</Latitude>
    <Longitude>-37.07731576561582</Longitude>
    <Role>Manager</Role>
    <Active>true</Active>
    <Distance>0.16302526483554125</Distance>
    <DistanceType>Air</DistanceType>
  </Tutor>
  <Tutor>
    <Id>371644392</Id>
    <FullName>David Azoulay</FullName>
    <CellNumber>059-7732072</CellNumber>
    <Email>david.azoulay@example.com</Email>
    <Password>$2a$11$/qwMMrAvqA4/wwOXBuEyIO/YeQogxS0WTXC8oJqLRTTPuQzztDSQW</Password>
    <CurrentAddress>Street 1, City 5</CurrentAddress>
    <Latitude>-84.80170936375745</Latitude>
    <Longitude>-144.56079589017256</Longitude>
    <Role>BeginnerTutor</Role>
    <Active>false</Active>
    <Distance>3.2511595348857947</Distance>
    <DistanceType>Walking</DistanceType>
  </Tutor>
  <Tutor>
    <Id>383247072</Id>
    <FullName>Dina Levin</FullName>
    <CellNumber>052-5158520</CellNumber>
    <Email>dina.levin@example.com</Email>
    <Password>$2a$11$xa76y7YPTqxUVs86wC2tS.zg92LttUTZsICaucZSdoWUVa.FUZSFa</Password>
    <CurrentAddress>Street 39, City 17</CurrentAddress>
    <Latitude>50.954227552910794</Latitude>
    <Longitude>-87.31748781521455</Longitude>
    <Role>MasterTutor</Role>
    <Active>true</Active>
    <Distance>0.6079371365613118</Distance>
    <DistanceType>Driving</DistanceType>
  </Tutor>
  <Tutor>
    <Id>246797016</Id>
    <FullName>Rivka Levy</FullName>
    <CellNumber>050-2416431</CellNumber>
    <Email>rivka.levy@example.com</Email>
    <Password>$2a$11$SejMz2E.E0RUAnBuzgh.EO1iB/j6heNfwyUnUhTul7DYr0sO/LOVO</Password>
    <CurrentAddress>Street 99, City 6</CurrentAddress>
    <Latitude>-77.3862261360735</Latitude>
    <Longitude>-62.804022101077535</Longitude>
    <Role>MasterTutor</Role>
    <Active>false</Active>
    <Distance>19.9362923478176</Distance>
    <DistanceType>Walking</DistanceType>
  </Tutor>
  <Tutor>
    <Id>347875018</Id>
    <FullName>David Azoulay</FullName>
    <CellNumber>057-3108212</CellNumber>
    <Email>david.azoulay@example.com</Email>
    <Password>$2a$11$JPwCEOM8LGskqK3M4aX.5eeApwSZWpDlGqRRleUPzzt.JiRclV.uC</Password>
    <CurrentAddress>Street 32, City 16</CurrentAddress>
    <Latitude>-50.34429266697707</Latitude>
    <Longitude>24.892060419210793</Longitude>
    <Role>MasterTutor</Role>
    <Active>false</Active>
    <Distance>17.228628098101375</Distance>
    <DistanceType>Air</DistanceType>
  </Tutor>
  <Tutor>
    <Id>305682595</Id>
    <FullName>Shira Sharabi</FullName>
    <CellNumber>052-1040179</CellNumber>
    <Email>shira.sharabi@example.com</Email>
    <Password>$2a$11$C6OOclDCzeKmHN9pd0Q/EeOIHKjtE5gi03d1dfN4kL4.UyF3brzNy</Password>
    <CurrentAddress>Street 83, City 2</CurrentAddress>
    <Latitude>-12.914430061531633</Latitude>
    <Longitude>164.66790959685056</Longitude>
    <Role>BeginnerTutor</Role>
    <Active>false</Active>
    <Distance>6.360599341077782</Distance>
    <DistanceType>Driving</DistanceType>
  </Tutor>
  <Tutor>
    <Id>234273774</Id>
    <FullName>David Mizrahi</FullName>
    <CellNumber>057-8060208</CellNumber>
    <Email>david.mizrahi@example.com</Email>
    <Password>$2a$11$tXyvcUcW7Q0rjkgxzelCGetHWtwCpcK.eV6D7Q3lhAVoFymgmJxW2</Password>
    <CurrentAddress>Street 2, City 1</CurrentAddress>
    <Latitude>68.27262879033043</Latitude>
    <Longitude>-97.38652178450307</Longitude>
    <Role>BeginnerTutor</Role>
    <Active>true</Active>
    <Distance>6.586374224103748</Distance>
    <DistanceType>Driving</DistanceType>
  </Tutor>
  <Tutor>
    <Id>321519306</Id>
    <FullName>Ariela Levy</FullName>
    <CellNumber>059-5747254</CellNumber>
    <Email>ariela.levy@example.com</Email>
    <Password>$2a$11$7cPL7DoNmYtyCmDMuVR6xej5MlBaEIuckPguQNzmXaRGuQLNARIfa</Password>
    <CurrentAddress>Street 28, City 10</CurrentAddress>
    <Latitude>-7.189666674329715</Latitude>
    <Longitude>164.16854459022466</Longitude>
    <Role>MasterTutor</Role>
    <Active>false</Active>
    <Distance>15.950705983630138</Distance>
    <DistanceType>Walking</DistanceType>
  </Tutor>
  <Tutor>
    <Id>379501805</Id>
    <FullName>Ariela Azoulay</FullName>
    <CellNumber>052-1082748</CellNumber>
    <Email>ariela.azoulay@example.com</Email>
    <Password>$2a$11$iK.M9gcihX4vVk/lBXBgQe1SPi/hp4RsBeHcUNgrEVe.5E1XEY.pa</Password>
    <CurrentAddress>Street 82, City 15</CurrentAddress>
    <Latitude>87.96638803451711</Latitude>
    <Longitude>-58.1166611441417</Longitude>
    <Role>MasterTutor</Role>
    <Active>true</Active>
    <Distance>16.324066171750754</Distance>
    <DistanceType>Walking</DistanceType>
  </Tutor>
  <Tutor>
    <Id>240751062</Id>
    <FullName>Eli Israelof</FullName>
    <CellNumber>051-3504767</CellNumber>
    <Email>eli.israelof@example.com</Email>
    <Password>$2a$11$fLfLMaqiCDjZ61kLmbpgrOMsbsito2KyqDyios86abzj2XGPwcBgO</Password>
    <CurrentAddress>Street 6, City 1</CurrentAddress>
    <Latitude>37.9733244452714</Latitude>
    <Longitude>-31.21057301389672</Longitude>
    <Role>MasterTutor</Role>
    <Active>true</Active>
    <Distance>8.98812240843614</Distance>
    <DistanceType>Walking</DistanceType>
  </Tutor>
  <Tutor>
    <Id>361821956</Id>
    <FullName>Dani Klein</FullName>
    <CellNumber>054-3002157</CellNumber>
    <Email>dani.klein@example.com</Email>
    <Password>$2a$11$Any2mAqo8cTEF8zkVR8rD.h9l1y2j676Vas29ONn46PEVR2JKwCCK</Password>
    <CurrentAddress>Street 55, City 7</CurrentAddress>
    <Latitude>-60.60824624395338</Latitude>
    <Longitude>-158.08605341745323</Longitude>
    <Role>BeginnerTutor</Role>
    <Active>true</Active>
    <Distance>19.631826906687387</Distance>
    <DistanceType>Driving</DistanceType>
  </Tutor>
  <Tutor>
    <Id>372188598</Id>
    <FullName>Rivka Peretz</FullName>
    <CellNumber>050-4440700</CellNumber>
    <Email>rivka.peretz@example.com</Email>
    <Password>$2a$11$3ufI2o33lWfJRCgRLfxJTufq01X2A.0WItevL/xm/YO7ikiVTHeUq</Password>
    <CurrentAddress>Street 70, City 12</CurrentAddress>
    <Latitude>70.37209260315768</Latitude>
    <Longitude>-129.05228789971324</Longitude>
    <Role>BeginnerTutor</Role>
    <Active>false</Active>
    <Distance>16.437640966060044</Distance>
    <DistanceType>Driving</DistanceType>
  </Tutor>
  <Tutor>
    <Id>384624117</Id>
    <FullName>David Sharabi</FullName>
    <CellNumber>050-9517465</CellNumber>
    <Email>david.sharabi@example.com</Email>
    <Password>$2a$11$ZfhNUpylUgh0SVxY75aGmea1.eOWRkHDLcu1/X0pDNSCmodNtI8C6</Password>
    <CurrentAddress>Street 82, City 17</CurrentAddress>
    <Latitude>40.50693288184945</Latitude>
    <Longitude>-75.32480504141834</Longitude>
    <Role>BeginnerTutor</Role>
    <Active>false</Active>
    <Distance>0.14939217728641374</Distance>
    <DistanceType>Walking</DistanceType>
  </Tutor>
  <Tutor>
    <Id>213046139</Id>
    <FullName>Dani Klein</FullName>
    <CellNumber>059-5170629</CellNumber>
    <Email>dani.klein@example.com</Email>
    <Password>$2a$11$AUsPpDLrQzb6GjmH/nOzuuEOBEyk6FkTgnHa/DBbUm24n.kLESP3m</Password>
    <CurrentAddress>Street 40, City 3</CurrentAddress>
    <Latitude>59.63136923798024</Latitude>
    <Longitude>-95.97982715206176</Longitude>
    <Role>BeginnerTutor</Role>
    <Active>true</Active>
    <Distance>1.6288623287482018</Distance>
    <DistanceType>Driving</DistanceType>
  </Tutor>
  <Tutor>
    <Id>371881023</Id>
    <FullName>Eli Amar</FullName>
    <CellNumber>050-5993847</CellNumber>
    <Email>eli.amar@example.com</Email>
    <Password>$2a$11$RN2l16xxBi/Zp2de/0SWWOosdojFOYkle8X4qp.PfakAdZ5Jdy4PW</Password>
    <CurrentAddress>Street 99, City 10</CurrentAddress>
    <Latitude>-70.7398511244355</Latitude>
    <Longitude>-93.79838483106768</Longitude>
    <Role>MasterTutor</Role>
    <Active>true</Active>
    <Distance>0.5912479566362694</Distance>
    <DistanceType>Air</DistanceType>
  </Tutor>
</ArrayOfTutor>